{
  "sqlite-explorer.displayName": "SQLite Explorer",
  "sqlite-explorer.description": "Potężna przeglądarka i edytor baz danych SQLite dla VS Code",
  "sqlite-explorer.customEditor.view.displayName": "SQLite Explorer",
  "sqlite-explorer.customEditor.option.displayName": "SQLite Explorer (Opcjonalnie)",
  "sqlite-explorer.commands.refresh.title": "Odśwież bazę danych",
  "sqlite-explorer.config.maxFileSize.markdownDescription": "Maksymalny rozmiar pliku w MB, który można otworzyć. Ustaw na 0 dla nieograniczonego.",
  "sqlite-explorer.config.defaultPageSize.markdownDescription": "Domyślna liczba wierszy do wyświetlenia na stronie.",
  "sqlite-explorer.config.maxRows.markdownDescription": "Maksymalna liczba wierszy do załadowania z tabeli. Ustaw na 0 dla nieograniczonego."
}
